simple_async_sqs/__init__.py
simple_async_sqs/lifecycle.py
simple_async_sqs/py.typed
simple_async_sqs/queue_client.py
simple_async_sqs-0.2.0.dist-info/WHEEL
simple_async_sqs-0.2.0.dist-info/METADATA
simple_async_sqs-0.2.0.dist-info/RECORD
