Metadata-Version: 2.3
Name: simple-async-sqs
Version: 0.2.0
Summary: Simple async SQS client
Author-email: jamie.cheng.chang@gmail.com
Requires-Dist: aiobotocore
Requires-Dist: types-aiobotocore[sqs] ; extra == 'stubs'
Requires-Python: >=3.10
Project-URL: Homepage, https://github.com/Jamie-Chang/simple-async-sqs
Project-URL: Repository, https://github.com/Jamie-Chang/simple-async-sqs
Provides-Extra: stubs
